aio_manager/__init__.py
aio_manager/commands/__init__.py
aio_manager/commands/example.py
aio_manager/commands/runserver.py
aio_manager/commands/shell.py
aio_manager/commands/ext/__init__.py
aio_manager/commands/ext/sqlalchemy.py
aio_manager-2.0.3.dist-info/DESCRIPTION.rst
aio_manager-2.0.3.dist-info/LICENSE.txt
aio_manager-2.0.3.dist-info/METADATA
aio_manager-2.0.3.dist-info/RECORD
aio_manager-2.0.3.dist-info/WHEEL
aio_manager-2.0.3.dist-info/metadata.json
aio_manager-2.0.3.dist-info/top_level.txt
