Metadata-Version: 2.0
Name: aio-manager
Version: 2.0.3
Summary: Script manager for aiohttp.
Home-page: https://github.com/rrader/aio_manager
Author: Sviatoslav Sydorenko (@webknjaz)
Author-email: antigluk@gmail.com
License: BSD
Platform: POSIX
Classifier: License :: OSI Approved :: BSD License
Classifier: Intended Audience :: Developers
Classifier: Programming Language :: Python :: 3
Classifier: Programming Language :: Python :: 3.5
Classifier: Programming Language :: Python :: 3.6
Classifier: Environment :: Web Environment
Classifier: Development Status :: 4 - Beta
Provides: aio_manager
Requires-Python: >=3.5
Requires-Dist: aiohttp
Requires-Dist: colorama
Provides-Extra: mysql
Requires-Dist: PyMySQL (>=0.7.5); extra == 'mysql'
Requires-Dist: sqlalchemy (>=0.9); extra == 'mysql'
Provides-Extra: postgres
Requires-Dist: psycopg2 (>=2.5.2); extra == 'postgres'
Requires-Dist: sqlalchemy (>=0.9); extra == 'postgres'
Provides-Extra: sa
Requires-Dist: sqlalchemy (>=0.9); extra == 'sa'
